find_new_git_url.py
ghec_migration.py
github_migration.py
jenkins_migration.py
make_private.py
update_topics_for_team.py
ghec_migration-3.1.2.dist-info/METADATA
ghec_migration-3.1.2.dist-info/WHEEL
ghec_migration-3.1.2.dist-info/entry_points.txt
ghec_migration-3.1.2.dist-info/top_level.txt
ghec_migration-3.1.2.dist-info/RECORD
