Metadata-Version: 2.1
Name: ghec-migration
Version: 3.1.2
Summary: A Python script for bulk migrating repos from one org to other org GitHub repositories using the API
Home-page: https://github.nike.com/mp-commerce-fulfillment/githubmigration
Author: Vamsi Maringanti
Author-email: vamsikrishna.maringanti@nike.com
License: MIT
Platform: UNKNOWN
Requires-Python: >=3.6
Requires-Dist: requests
Requires-Dist: regex
Requires-Dist: PyInquirer
Requires-Dist: python-jenkins
Requires-Dist: pbr
Requires-Dist: multi-key-dict
Requires-Dist: xmltodict
